[
  {
    "userId": "4f931d2c-1206-5067-2883-84b40697a6d5",
    "name": "c",
    "login": "c",
    "password": "c",
    "sessionKeys": [],
    "email": "c",
    "address": "c",
    "telephone": "c"
  },
  {
    "userId": "ca9796fc-1fd1-8054-aa3a-dc983d6a6891",
    "name": "user1",
    "login": "user1",
    "password": "user1",
    "sessionKeys": [],
    "email": "user1",
    "gender": "female",
    "address": "address 1",
    "telephone": "123"
  },
  {
    "userId": "4a4eca04-2fda-af86-ba63-083f524ed971",
    "name": "a",
    "login": "a",
    "password": "a",
    "sessionKeys": [],
    "email": "a",
    "gender": "a",
    "address": "a",
    "telephone": "a"
  },
  {
    "userId": "ca9796fc-1fd1-8054-aa3a-dc983d6a6891",
    "sessionKeys": [],
    "name": "user1",
    "login": "user1",
    "password": "user1",
    "email": "user1",
    "gender": "female",
    "address": "address 1",
    "telephone": "123"
  }
]